discrete_continuous_embed_readout/__init__.py
discrete_continuous_embed_readout/discrete_continuous_embed_readout.py
discrete_continuous_embed_readout-0.1.12.dist-info/METADATA
discrete_continuous_embed_readout-0.1.12.dist-info/WHEEL
discrete_continuous_embed_readout-0.1.12.dist-info/licenses/LICENSE
discrete_continuous_embed_readout-0.1.12.dist-info/RECORD
