Metadata-Version: 2.4
Name: discrete-continuous-embed-readout
Version: 0.1.12
Summary: Discrete Continuous Embed Readout
Project-URL: Homepage, https://pypi.org/project/discrete-continuous-embed-readout/
Project-URL: Repository, https://github.com/lucidrains/discrete-continuous-embed-readout
Author-email: Phil Wang <lucidrains@gmail.com>
License: MIT License
License-File: LICENSE
Keywords: action spaces,artificial intelligence,deep learning
Classifier: Development Status :: 4 - Beta
Classifier: Intended Audience :: Developers
Classifier: License :: OSI Approved :: MIT License
Classifier: Programming Language :: Python :: 3.9
Classifier: Topic :: Scientific/Engineering :: Artificial Intelligence
Requires-Python: >=3.9
Requires-Dist: beartype
Requires-Dist: einops>=0.8.1
Requires-Dist: torch>=2.8
Provides-Extra: examples
Provides-Extra: test
Requires-Dist: pytest; extra == 'test'
Requires-Dist: x-transformers; extra == 'test'
